morsedecode/__init__.py
morsedecode/__main__.py
morsedecode/cli.py
morsedecode/py.typed
morsedecode-1.0.1.dist-info/LICENSE
morsedecode-1.0.1.dist-info/METADATA
morsedecode-1.0.1.dist-info/WHEEL
morsedecode-1.0.1.dist-info/entry_points.txt
morsedecode-1.0.1.dist-info/top_level.txt
morsedecode-1.0.1.dist-info/RECORD
